AUTHORS
LICENSE
MANIFEST.in
README.rst
setup.py
django_secure_input.egg-info/PKG-INFO
django_secure_input.egg-info/SOURCES.txt
django_secure_input.egg-info/dependency_links.txt
django_secure_input.egg-info/not-zip-safe
django_secure_input.egg-info/requires.txt
django_secure_input.egg-info/top_level.txt
secure_input/__init__.py
secure_input/defaults.py
secure_input/fields.py
secure_input/models.py
secure_input/tests.py
secure_input/utils.py
secure_input/widgets.py
secure_input/static/secure_input/bootstrap-wysiwyg/LICENSE
secure_input/static/secure_input/bootstrap-wysiwyg/README.md
secure_input/static/secure_input/bootstrap-wysiwyg/bootstrap-wysiwyg.js
secure_input/static/secure_input/bootstrap-wysiwyg/index.css
secure_input/static/secure_input/bootstrap-wysiwyg/index.html
secure_input/static/secure_input/bootstrap-wysiwyg/promo-868x350.png
secure_input/static/secure_input/bootstrap-wysiwyg/republish.sh
secure_input/static/secure_input/bootstrap-wysiwyg/external/jquery.hotkeys.js
secure_input/static/secure_input/bootstrap-wysiwyg/external/google-code-prettify/lang-apollo.js
secure_input/static/secure_input/bootstrap-wysiwyg/external/google-code-prettify/lang-basic.js
secure_input/static/secure_input/bootstrap-wysiwyg/external/google-code-prettify/lang-clj.js
secure_input/static/secure_input/bootstrap-wysiwyg/external/google-code-prettify/lang-css.js
secure_input/static/secure_input/bootstrap-wysiwyg/external/google-code-prettify/lang-dart.js
secure_input/static/secure_input/bootstrap-wysiwyg/external/google-code-prettify/lang-erlang.js
secure_input/static/secure_input/bootstrap-wysiwyg/external/google-code-prettify/lang-go.js
secure_input/static/secure_input/bootstrap-wysiwyg/external/google-code-prettify/lang-hs.js
secure_input/static/secure_input/bootstrap-wysiwyg/external/google-code-prettify/lang-lisp.js
secure_input/static/secure_input/bootstrap-wysiwyg/external/google-code-prettify/lang-llvm.js
secure_input/static/secure_input/bootstrap-wysiwyg/external/google-code-prettify/lang-lua.js
secure_input/static/secure_input/bootstrap-wysiwyg/external/google-code-prettify/lang-matlab.js
secure_input/static/secure_input/bootstrap-wysiwyg/external/google-code-prettify/lang-ml.js
