Metadata-Version: 1.1
Name: django-secure-input
Version: 0.9.1
Summary: django-secure-input provides custom form fields to render wysiwyg editor instead of regular textareas. It takes care of cleaning html for you too. With its super secure defaults you do not want to modified it's whitelisting rules.
Home-page: https://github.com/rochapps/django-secure-input/
Author: RochApps, LLC
Author-email: info@rochapps.com
License: BSD
Platform: UNKNOWN
Classifier: Topic :: Internet :: WWW/HTTP :: Dynamic Content
Classifier: Intended Audience :: Developers
Classifier: Programming Language :: Python
Classifier: Programming Language :: Python :: 2.6
Classifier: Programming Language :: Python :: 2.7
Classifier: Framework :: Django
Classifier: Development Status :: 4 - Beta
Classifier: Operating System :: OS Independent
